DePTH/__init__.py
DePTH/_utils.py
DePTH/cv.py
DePTH/main.py
DePTH/predict.py
DePTH/train.py
DePTH/data/ensemble_seeds_20.txt
DePTH/data/for_encoders/AAidx_PCA.csv
DePTH/data/for_encoders/Atchley_factors.csv
DePTH/data/for_encoders/HLA_II_pseudo_45.csv
DePTH/data/for_encoders/HLA_I_pseudo_40.csv
DePTH/data/for_encoders/blosum62.csv
DePTH/data/for_encoders/blosum62_X.csv
DePTH/data/for_encoders/combo_xcr.tsv
DePTH/data/trained_models/HLA_I/model_1383_4065_6352/fingerprint.pb
DePTH/data/trained_models/HLA_I/model_1383_4065_6352/keras_metadata.pb
DePTH/data/trained_models/HLA_I/model_1383_4065_6352/saved_model.pb
DePTH/data/trained_models/HLA_I/model_1383_4065_6352/variables/variables.data-00000-of-00001
DePTH/data/trained_models/HLA_I/model_1383_4065_6352/variables/variables.index
DePTH/data/trained_models/HLA_I/model_1608_8784_6229/fingerprint.pb
DePTH/data/trained_models/HLA_I/model_1608_8784_6229/keras_metadata.pb
DePTH/data/trained_models/HLA_I/model_1608_8784_6229/saved_model.pb
DePTH/data/trained_models/HLA_I/model_1608_8784_6229/variables/variables.data-00000-of-00001
DePTH/data/trained_models/HLA_I/model_1608_8784_6229/variables/variables.index
DePTH/data/trained_models/HLA_I/model_1729_4240_6624/fingerprint.pb
DePTH/data/trained_models/HLA_I/model_1729_4240_6624/keras_metadata.pb
DePTH/data/trained_models/HLA_I/model_1729_4240_6624/saved_model.pb
DePTH/data/trained_models/HLA_I/model_1729_4240_6624/variables/variables.data-00000-of-00001
DePTH/data/trained_models/HLA_I/model_1729_4240_6624/variables/variables.index
DePTH/data/trained_models/HLA_I/model_2249_2812_8150/fingerprint.pb
DePTH/data/trained_models/HLA_I/model_2249_2812_8150/keras_metadata.pb
DePTH/data/trained_models/HLA_I/model_2249_2812_8150/saved_model.pb
DePTH/data/trained_models/HLA_I/model_2249_2812_8150/variables/variables.data-00000-of-00001
DePTH/data/trained_models/HLA_I/model_2249_2812_8150/variables/variables.index
DePTH/data/trained_models/HLA_I/model_2569_2343_341/fingerprint.pb
depth-2.1.0.dist-info/licenses/LICENSE
depth-2.1.0.dist-info/METADATA
depth-2.1.0.dist-info/WHEEL
depth-2.1.0.dist-info/entry_points.txt
depth-2.1.0.dist-info/top_level.txt
depth-2.1.0.dist-info/RECORD
