Metadata-Version: 2.4
Name: DePTH
Version: 2.1.0
Summary: DePTH provides neural network models for sequence-based TCR and HLA association prediction
Home-page: https://github.com/Sun-lab/DePTH
Author: Si Liu
Author-email: liusi2019@gmail.com
License: MIT
Project-URL: Documentation, https://github.com/Sun-lab/DePTH
Project-URL: Bug Tracker, https://github.com/Sun-lab/DePTH/issues
Classifier: Programming Language :: Python :: 3
Classifier: License :: OSI Approved :: MIT License
Classifier: Operating System :: OS Independent
Requires-Python: >=3.9
License-File: LICENSE
Requires-Dist: scikit-learn>=1.0.2
Requires-Dist: tensorflow<2.15.1,>=2.4.1
Requires-Dist: pandas>=1.4.2
Requires-Dist: numpy>=1.21.5
Dynamic: author
Dynamic: author-email
Dynamic: classifier
Dynamic: description
Dynamic: description-content-type
Dynamic: home-page
Dynamic: license
Dynamic: license-file
Dynamic: project-url
Dynamic: requires-dist
Dynamic: requires-python
Dynamic: summary
